{"type":"FeatureCollection","features":[{"geometry": {"type": "Point", "coordinates": [68.276, 25.5936]}, "type": "Feature", "id": 0, "properties": {"Roads_KMs_": 293, "Bridges": 3, "Latitude": 25.5936, "Location": "Matiari", "Longitude": 68.276}},{"geometry": {"type": "Point", "coordinates": [69.0149, 25.5252]}, "type": "Feature", "id": 1, "properties": {"Roads_KMs_": 0, "Bridges": 0, "Latitude": 25.5252, "Location": "Mirpurkhas", "Longitude": 69.0149}},{"geometry": {"type": "Point", "coordinates": [69.5358, 25.2778]}, "type": "Feature", "id": 2, "properties": {"Roads_KMs_": 0, "Bridges": 0, "Latitude": 25.2778, "Location": "Tharparkar", "Longitude": 69.5358}}]}