{"type":"FeatureCollection","features":[{"geometry": {"type": "Point", "coordinates": [74.0944, 35.4194]}, "type": "Feature", "id": 0, "properties": {"Latitude": 35.4194, "Location": "Chilas", "Longitude": 74.0944}},{"geometry": {"type": "Point", "coordinates": [73.9427, 35.4349]}, "type": "Feature", "id": 1, "properties": {"Latitude": 35.4349, "Location": "Diamer", "Longitude": 73.9427}},{"geometry": {"type": "Point", "coordinates": [74.8561, 35.3469]}, "type": "Feature", "id": 2, "properties": {"Latitude": 35.3469, "Location": "Astore", "Longitude": 74.8561}},{"geometry": {"type": "Point", "coordinates": [73.6477, 36.0488]}, "type": "Feature", "id": 3, "properties": {"Latitude": 36.0488, "Location": "Ghizer", "Longitude": 73.6477}}]}